{
  "kind": "collectionType",
  "collectionName": "cji_medios",
  "info": {
    "singularName": "cji-medio",
    "pluralName": "cji-medios",
    "displayName": "CJI medios"
  },
  "options": {
    "draftAndPublish": true
  },
  "pluginOptions": {},
  "attributes": {
    "Titulo": {
      "type": "string",
      "required": true
    },
    "imagen": {
      "type": "media",
      "multiple": false,
      "required": true,
      "allowedTypes": [
        "images"
      ]
    },
    "link": {
      "type": "string",
      "required": true
    },
    "Contenido": {
      "type": "text",
      "required": true
    },
    "slug": {
      "type": "uid",
      "targetField": "link",
      "required": true
    }
  }
}
